MANIFEST.in
README
index.html
setup.py
wb.ini
wb.py
wbmgmt.py
WB.egg-info/PKG-INFO
WB.egg-info/SOURCES.txt
WB.egg-info/dependency_links.txt
WB.egg-info/top_level.txt
_img/admin.png
_img/del.gif
_img/do.gif
_img/edit_form.jpg
_img/modify.jpg
_img/newdoc.jpg
_img/nul.gif
_img/qm.png
_img/up.gif
_img/wb.ico
_img/wb.png
_lang_it/about.html
_lang_it/config.html
_lang_it/copyright.html
_lang_it/help.html
_lang_it/install.html
_lang_it/usage.html
_lang_it/voc.ini
_lang_it/wb.ini
_lang_it/wbfaq.html
_lang_us/about.html
_lang_us/config.html
_lang_us/copyright.html
_lang_us/help.html
_lang_us/install.html
_lang_us/usage.html
_lang_us/voc.ini
_lang_us/wbfaq.html