Metadata-Version: 1.0
Name: WB
Version: 7.1
Summary: A CGI program to manage 'Billboards' where documents can beposted (and edited and removed) through a simple WEB interface.
Home-page: UNKNOWN
Author: Luca Fini
Author-email: lfini@arcetri.astro.it
License: GPL
Keywords: CGI CMS
Platform: UNKNOWN
Classifier: Development Status :: 5 - Production/Stable
Classifier: Topic :: Internet :: WWW/HTTP :: Dynamic Content :: CGI Tools/Libraries
Classifier: Natural Language :: English
Classifier: Natural Language :: Italian
Classifier: Intended Audience :: System Administrators
